{"id":308101,"title":" Castanha-de-caju apimentada","description":"Castanha-de-caju crocante e agridoce sem precisar ir ao forno: é na frigideira que tudo acontece! O truque é misturar bem as castanhas com azeite e água para o tempero ficar grudadinho. Viciante! ","imageUrl":"https://cdn.panelinha.com.br/receita/1565027807988-_JW_9242.jpg","slug":" castanha-de-caju-apimentada","content":{"light":false,"author":"Panelinha","serves":"Até 4 porções","keyword":"castanha-de-caju","hasVideo":false,"prepareTime":"Pá-Pum","recipeSteps":[{"body":"<ol>\n<li>Numa tigela, coloque as castanhas e tempere com as especiarias, o a&ccedil;&uacute;car e sal a gosto. Acrescente a &aacute;gua, o azeite e misture bem para envolver as castanhas com os temperos.</li>\n<li>Leve uma frigideira m&eacute;dia antiaderente ao fogo baixo.&nbsp;Coloque as castanhas e deixe aquecer por 1 minuto, sem mexer,&nbsp;at&eacute; o a&ccedil;&uacute;car come&ccedil;ar a derreter. Mantenha as castanhas em fogo baixo, mexendo de vez em quando por 15 minutos, at&eacute; ficarem douradas e sequinhas &ndash; evite mexer em excesso pois as especiarias podem se soltar das castanhas.</li>\n<li>Transfira as castanhas para uma assadeira pequena (ou travessa) e deixe esfriar completamente antes de servir ou armazenar. Sirva como petisco no happy hour, com saladas, risotos ou sopas.</li>\n</ol>","type":"preparo","title":"","sequence":0,"superTitle":"","ingredients":[{"quantity":"1","sequence":0,"connector":"de","measureId":27,"complement":"torrada sem sal (cerca de 150 g)","ingredientId":322},{"quantity":"½","sequence":1,"connector":"de","measureId":25,"complement":"em pó","ingredientId":176},{"quantity":"¼ de","sequence":2,"connector":"de","measureId":25,"complement":"","ingredientId":318},{"quantity":"1","sequence":3,"connector":"de","measureId":25,"complement":"","ingredientId":64},{"quantity":"½","sequence":4,"connector":"de","measureId":25,"complement":"","ingredientId":66},{"quantity":"½","sequence":5,"connector":"de","measureId":25,"complement":"(ou óleo)","ingredientId":104},{"quantity":"","sequence":6,"connector":"","complement":"","ingredientId":971}]},{"type":"produto","title":"Compre o que você precisa","columns":3,"sequence":1,"subtitle":"Loja Panelinha ","isCarousel":false,"productCells":[{"id":10,"tag":"","imageUrl":"https://cdn.panelinha.com.br/produto/1562856483086-51TRfZAoOoL._SL1000_.jpg","sequence":0,"customTitle":"Tigela média [pimenta-do-reino], Acervo Panelinha","storeUrl":"https://amzn.to/2JtZ6ZC","image":"1562856483086-51TRfZAoOoL._SL1000_","imageLocation":"cdn","imageRatio":1,"imageFormat":"jpg","imageFolder":"produto"},{"id":35,"tag":"","imageUrl":"https://cdn.panelinha.com.br/produto/1562864040926-frigibailarini.jpg","sequence":1,"customTitle":"Frigideira de alumínio Siena, Baillarini ","storeUrl":"https://amzn.to/2WTm04J","image":"1562864040926-frigibailarini","imageLocation":"cdn","imageRatio":1.57563025210084,"imageFormat":"jpg","imageFolder":"produto"},{"id":190,"tag":"","imageUrl":"https://cdn.panelinha.com.br/produto/1563391007000-617EaRdBolL._SL1500_.jpg","sequence":2,"customTitle":"Espátula de silicone, Staub ","storeUrl":"https://amzn.to/3bB3phV","image":"1563391007000-617EaRdBolL._SL1500_","imageLocation":"cdn","imageRatio":2.40770465489567,"imageFormat":"jpg","imageFolder":"produto"},{"id":200,"tag":"","imageUrl":"https://cdn.panelinha.com.br/produto/1563391822574-31HLUmg49gL.jpg","sequence":3,"customTitle":"Assadeira de alumínio antiaderente, Tramontina ","storeUrl":"https://amzn.to/3dIprky","image":"1563391822574-31HLUmg49gL","imageLocation":"cdn","imageRatio":0.388,"imageFormat":"jpg","imageFolder":"produto"},{"id":17,"tag":"","imageUrl":"https://cdn.panelinha.com.br/produto/1562856967083-51n0wnC7UTL._SL1000_.jpg","sequence":4,"customTitle":"Trio de cumbucas, Acervo Panelinha","storeUrl":"https://amzn.to/3dIrXaz","image":"1562856967083-51n0wnC7UTL._SL1000_","imageLocation":"cdn","imageRatio":1.00704934541793,"imageFormat":"jpg","imageFolder":"produto"},{"id":67,"tag":"","imageUrl":"https://cdn.panelinha.com.br/produto/1562871111954-colheresmedidoras.jpg","sequence":5,"customTitle":"Colheres medidoras ","storeUrl":"https://amzn.to/2wFcO9D","image":"1562871111954-colheresmedidoras","imageLocation":"cdn","imageRatio":1,"imageFormat":"jpg","imageFolder":"produto"}]}],"customServes":""},"pageType":"receita","categories":[{"id":1,"title":"Aperitivos","page_id":308101},{"id":2,"title":"Acompanhamentos","page_id":308101},{"id":174,"title":"Happy hour","page_id":308101},{"id":179,"title":"Cozinha Prática","page_id":308101},{"id":308,"title":"Caseiro","page_id":308101}],"cuisines":[{"id":1,"title":"contemporânea","page_id":308101},{"id":6,"title":"oriental","page_id":308101},{"id":14,"title":"caseira","page_id":308101},{"id":16,"title":"vegetariana","page_id":308101},{"id":17,"title":"prática","page_id":308101},{"id":40,"title":"sem glúten","page_id":308101}],"measures":[{"id":25,"title":"colher (chá)","page_id":308101},{"id":27,"title":"xícara (chá)","page_id":308101}],"ingredients":[{"id":64,"title":"açúcar","page_id":308101,"links":[]},{"id":66,"title":"água","page_id":308101,"links":[]},{"id":104,"title":"azeite","page_id":308101,"links":[]},{"id":176,"title":"gengibre","page_id":308101,"links":[]},{"id":318,"title":"pimenta-de-caiena","page_id":308101,"links":[]},{"id":322,"title":"castanhas-de-caju","page_id":308101,"links":[]},{"id":971,"title":"sal a gosto","page_id":308101,"links":[]}],"childrenPages":[{"imageurl":"https://cdn.panelinha.com.br/receita/1417572000000-Kulfi-de-cenoura-sorvete-indiano.jpg","slug":"Kulfi-de-cenoura-sorvete-indiano","join_id":308101,"page_id":305455,"customtitle":"Kulfi de cenoura (sorvete indiano)","tag":"","sequence":2,"image_url":"https://cdn.panelinha.com.br/receita/1417572000000-Kulfi-de-cenoura-sorvete-indiano.jpg","image":"1417572000000-Kulfi-de-cenoura-sorvete-indiano","image_format":"jpg","image_ratio":0.665644171779141,"image_location":"cdn","image_folder":"receita"},{"imageurl":"https://cdn.panelinha.com.br/receita/1565026064395-_JW_9269.jpg","slug":"salada-arroz-curry","join_id":308101,"page_id":308100,"customtitle":"Salada de arroz com curry","tag":"","sequence":0,"image_url":"https://cdn.panelinha.com.br/receita/1565026064395-_JW_9269.jpg","image":"1565026064395-_JW_9269","image_format":"jpg","image_ratio":0.665644171779141,"image_location":"cdn","image_folder":"receita"},{"imageurl":"https://cdn.panelinha.com.br/receita/1565027807988-_JW_9242.jpg","slug":" castanha-de-caju-apimentada","join_id":308101,"page_id":308101,"customtitle":" Castanha-de-caju apimentada","tag":"","sequence":1,"image_url":"https://cdn.panelinha.com.br/receita/1565027807988-_JW_9242.jpg","image":"1565027807988-_JW_9242","image_format":"jpg","image_ratio":0.665644171779141,"image_location":"cdn","image_folder":"receita"}],"image":"1565027807988-_JW_9242","imageLocation":"cdn","imageRatio":0.665644171779141,"imageFormat":"jpg","imageFolder":"receita","relatedContent":[],"isFavorite":false}