{"id":5115,"title":"Batata frita tradicional","description":"A batata frita é uma delícia, mas tem de ser bem feita! Com as nossas dicas, você terá batatas sequinhas e crocantes.","imageUrl":"https://cdn.panelinha.com.br/receita/953607600000-Batata-frita-tradicional.jpg","slug":"Batata-frita-tradicional","content":{"light":false,"author":"Panelinha","serves":"Até 4 porções","keyword":"batata","hasVideo":false,"prepareTime":"Pá-Pum","recipeSteps":[{"body":"<ol>\n<li>Quando voc&ecirc; for comprar a batata, procure se informar se ela &eacute; do tipo seca - na feira, os vendedores sabem dizer com precis&atilde;o. Lave muito bem a casca das batatas sob &aacute;gua corrente, esfregando uma escovinha limpa.&nbsp;</li>\n<li>Descasque as batatas e coloque numa panela ou tigela com &aacute;gua (isso evita que as batatas oxidem e escure&ccedil;am em contato com ar). Depois de descascadas, escolha a maneira que voc&ecirc; quer cort&aacute;-las: pode ser em palitos grossos ou finos, rodelas, chips, em cubinhos, etc. O importante &eacute; que o corte seja uniforme.&nbsp;</li>\n<li>Coloque o &oacute;leo em uma panela de paredes altas e leve ao fogo para aquecer. Coloque um palito de f&oacute;sforo no &oacute;leo para saber quando se ele est&aacute; no ponto. Quando o palito ascender, retire-o da panela com uma escumadeira.&nbsp;</li>\n<li>Seque as batatas em um pano de prato limpo e coloque-as dentro da panela com &oacute;leo. Mexa ligeiramente para que elas n&atilde;o grudem. Em seguida, pare de mexer e deixe fritar. Essa primeira etapa estar&aacute; pronta quando as batatas estiverem esbranqui&ccedil;adas e macias. A inten&ccedil;&atilde;o &eacute; que elas apenas cozinhem.&nbsp;</li>\n<li>Retire as batatas da panela com uma escumadeira e coloque-as para escorrer em um prato forrado com papel-toalha. Essa etapa pode ser feita com bastante anteced&ecirc;ncia, deixando para fazer a segunda etapa na hora que a refei&ccedil;&atilde;o for servida.&nbsp;</li>\n<li>Para fazer a segunda etapa, volte a aquecer a panela com o mesmo &oacute;leo. Utilize o palito de f&oacute;sforo para saber se o &oacute;leo est&aacute; quente. Quando o palito ascender, retire-o da panela e coloque as batatas na panela. Mexa ligeiramente para que n&atilde;o grudem. Pare de mexer e deixe fritar at&eacute; que elas fiquem bem douradas. Esse m&eacute;todo deixar&aacute; as batatas muito crocantes por fora e bem macias por dentro.&nbsp;</li>\n<li>Retire as batatas da panela com a ajuda de uma escumadeira e coloque-as para escorrer em um prato forrado com papel-toalha. Tempere com sal a gosto e sirva imediatamente.</li>\n</ol>","type":"preparo","title":"","sequence":0,"superTitle":"","ingredients":[{"quantity":"1,5","sequence":0,"connector":"de","measureId":18,"complement":"","ingredientId":125},{"quantity":"1","sequence":1,"connector":"de","measureId":155,"complement":"","ingredientId":95},{"quantity":"","sequence":2,"connector":"","measureId":1,"complement":"a gosto","ingredientId":111}]},{"type":"produto","title":"Compre o que você precisa","columns":4,"sequence":1,"subtitle":"Loja Panelinha ","isCarousel":false,"productCells":[{"id":49,"tag":"","imageUrl":"https://cdn.panelinha.com.br/produto/1562868383923-oxopretp.jpg","sequence":0,"customTitle":"Descascador, Oxo","storeUrl":"https://amzn.to/2yfHQFb","image":"1562868383923-oxopretp","imageLocation":"cdn","imageRatio":1,"imageFormat":"jpg","imageFolder":"produto"},{"id":48,"tag":"","imageUrl":"https://cdn.panelinha.com.br/produto/1562868147815-bowlhercules.jpg","sequence":1,"customTitle":"Tigela de inox, Hercules "},{"id":64,"tag":"","imageUrl":"https://cdn.panelinha.com.br/produto/1562870759084-51muMh67gLL._SL1500_.jpg","sequence":2,"customTitle":"Faca de chefe, Zwilling ","storeUrl":"https://amzn.to/2Us3pLq","image":"1562870759084-51muMh67gLL._SL1500_","imageLocation":"cdn","imageRatio":7.07547169811321,"imageFormat":"jpg","imageFolder":"produto"},{"id":61,"tag":"","imageUrl":"https://cdn.panelinha.com.br/produto/1562870467930-tabuatramonta.jpg","sequence":3,"customTitle":"Tábua de madeira, Tramontina ","storeUrl":"https://amzn.to/2xyk6Mg","image":"1562870467930-tabuatramonta","imageLocation":"cdn","imageRatio":1,"imageFormat":"jpg","imageFolder":"produto"},{"id":145,"tag":"","imageUrl":"https://cdn.panelinha.com.br/produto/1563375779466-812owACi0zL._SL1500_.jpg","sequence":4,"customTitle":"Conjunto com 3 panelas de aço inoxidável, Zwilling J.A. Henckels","storeUrl":"https://amzn.to/2xDrEgB","image":"1563375779466-812owACi0zL._SL1500_","imageLocation":"cdn","imageRatio":0.638,"imageFormat":"jpg","imageFolder":"produto"},{"id":52,"tag":"","imageUrl":"https://cdn.panelinha.com.br/produto/1562868670581-escuma_2.jpg","sequence":5,"customTitle":"Escumadeira de inox, Hercules ","storeUrl":"https://amzn.to/2WW5zEO","image":"1562868670581-escuma_2","imageLocation":"cdn","imageRatio":0.652,"imageFormat":"jpg","imageFolder":"produto"},{"id":43,"tag":"","imageUrl":"https://cdn.panelinha.com.br/produto/1562865522292-colherstaub.jpg","sequence":6,"customTitle":"Colher de silicone, Staub","storeUrl":"https://amzn.to/2ynGnNr","image":"1562865522292-colherstaub","imageLocation":"cdn","imageRatio":2.55536626916525,"imageFormat":"jpg","imageFolder":"produto"},{"id":10,"tag":"","imageUrl":"https://cdn.panelinha.com.br/produto/1562856483086-51TRfZAoOoL._SL1000_.jpg","sequence":7,"customTitle":"Tigela média [pimenta-do-reino], Acervo Panelinha","storeUrl":"https://amzn.to/2JtZ6ZC","image":"1562856483086-51TRfZAoOoL._SL1000_","imageLocation":"cdn","imageRatio":1,"imageFormat":"jpg","imageFolder":"produto"}]}]},"pageType":"receita","categories":[{"id":1,"title":"Aperitivos","page_id":5115},{"id":2,"title":"Acompanhamentos","page_id":5115},{"id":302,"title":"Básico","page_id":5115}],"cuisines":[{"id":5,"title":"inglesa","page_id":5115},{"id":7,"title":"americana","page_id":5115},{"id":16,"title":"vegetariana","page_id":5115},{"id":19,"title":"clássica","page_id":5115},{"id":40,"title":"sem glúten","page_id":5115}],"measures":[{"id":1,"title":null,"page_id":5115},{"id":18,"title":"kg","page_id":5115},{"id":155,"title":"litro","page_id":5115}],"ingredients":[{"id":95,"title":"óleo","page_id":5115,"links":[]},{"id":111,"title":"sal","page_id":5115,"links":[]},{"id":125,"title":"batata","page_id":5115,"links":[]}],"childrenPages":[{"imageurl":"https://cdn.panelinha.com.br/receita/1480903200000-Bife-grelhado-com-vinagrete.jpg","slug":"Bife-grelhado-com-vinagrete","join_id":5115,"page_id":306016,"customtitle":"Bife grelhado com vinagrete","tag":"prato principal","sequence":1,"image_url":"https://cdn.panelinha.com.br/receita/1480903200000-Bife-grelhado-com-vinagrete.jpg","image":"1480903200000-Bife-grelhado-com-vinagrete","image_format":"jpg","image_ratio":0.665644171779141,"image_location":"cdn","image_folder":"receita"},{"imageurl":"https://cdn.panelinha.com.br/receita/1499453424040-suco-de-manga.jpg","slug":"Suco-de-manga-com-limao","join_id":5115,"page_id":6015,"customtitle":"Suco de manga com limão","tag":"bebida","sequence":0,"image_url":"https://cdn.panelinha.com.br/receita/1499453424040-suco-de-manga.jpg","image":"1499453424040-suco-de-manga","image_format":"jpg","image_ratio":0.665644171779141,"image_location":"cdn","image_folder":"receita"},{"imageurl":"https://cdn.panelinha.com.br/receita/1529440699659-receita-sorvete-banana.jpg","slug":"Sorvete-de-banana","join_id":5115,"page_id":305598,"customtitle":"Sorvete de banana","tag":"sobremesa","sequence":3,"image_url":"https://cdn.panelinha.com.br/receita/1529440699659-receita-sorvete-banana.jpg","image":"1529440699659-receita-sorvete-banana","image_format":"jpg","image_ratio":0.665644171779141,"image_location":"cdn","image_folder":"receita"},{"imageurl":"https://cdn.panelinha.com.br/receita/953607600000-Batata-frita-tradicional.jpg","slug":"Batata-frita-tradicional","join_id":5115,"page_id":5115,"customtitle":"Batata frita tradicional","tag":"acompanhamento","sequence":2,"image_url":"https://cdn.panelinha.com.br/receita/953607600000-Batata-frita-tradicional.jpg","image":"953607600000-Batata-frita-tradicional","image_format":"jpg","image_ratio":0.665644171779141,"image_location":"cdn","image_folder":"receita"}],"image":"953607600000-Batata-frita-tradicional","imageLocation":"cdn","imageRatio":0.665644171779141,"imageFormat":"jpg","imageFolder":"receita","relatedContent":[{"title":"Batata ao curry","imageUrl":"https://cdn.panelinha.com.br/receita/953607600000-Batatas-ao-curry.jpg","pageType":"receita","slug":"Batatas-ao-curry","description":"Saia do lugar-comum e impressione os seus convidados com o sabor desta batata ao curry.","image":"953607600000-Batatas-ao-curry","imageFormat":"jpg","imageRatio":0.665644171779141,"imageLocation":"cdn","imageFolder":"receita"},{"title":"Batata à indiana (tari aloo)","imageUrl":"https://cdn.panelinha.com.br/receita/1534340256892-batatas-a-indiana-cortada-para-receita.jpg","pageType":"receita","slug":"Batatas-a-indiana-tari-aloo","description":"Adora especiarias, adora combinar sabores, mas fica com medo de errar? Essa receita é para você! Você aprende novas combinações e de quebra ganha um acompanhamento bem perfumado, diferentão e que transporta a refeição direto para a Índia.","image":"1534340256892-batatas-a-indiana-cortada-para-receita","imageFormat":"jpg","imageRatio":0.665644171779141,"imageLocation":"cdn","imageFolder":"receita"},{"title":"Chips assado de casca de batata","imageUrl":"https://cdn.panelinha.com.br/receita/1584735858726-chips%20de%20casca.jpg","pageType":"receita","slug":"chips-assado-de-casca-de-batata","description":"Você nunca mais vai jogar as cascas da batata fora. Elas ficam sequinhas, crocantes, perfeitas para dar um toque final à preparos como sopas, saladas e purês. \n","image":"1584735858726-chips de casca","imageFormat":"jpg","imageRatio":0.665644171779141,"imageLocation":"cdn","imageFolder":"receita"},{"title":"Purê de batata (6 porções)","imageUrl":"https://cdn.panelinha.com.br/receita/1570633061633-pure%CC%82.jpg","pageType":"receita","slug":"Pure-de-batatas-para-a-familia","description":"Tão simples, tão delicioso. Ah, mas espere aí: purê tem segredo para ficar perfeito! Nesta receita a gente conta qual é.","image":"1570633061633-purê","imageFormat":"jpg","imageRatio":0.665644171779141,"imageLocation":"cdn","imageFolder":"receita"},{"title":"Batata bolinha ao murro com alecrim","imageUrl":"https://cdn.panelinha.com.br/receita/1530643342944-batata-ao-murro.jpg","pageType":"receita","slug":"Batata-bolinha-ao-murro-com-alecrim","description":"Esse acompanhamento faz a linha fácil e charmoso. Com essas batatas, qualquer bifinho vira especial do dia. A batata bolinha cozida, amassada e assada com ervas, fica crocante por fora, macia por dentro e toda perfumada.","image":"1530643342944-batata-ao-murro","imageFormat":"jpg","imageRatio":0.665644171779141,"imageLocation":"cdn","imageFolder":"receita"},{"title":"Batata à moda libanesa","imageUrl":"https://cdn.panelinha.com.br/receita/1142391600000-Batata-a-moda-libanesa.jpg","pageType":"receita","slug":"Batata-a-moda-libanesa","description":"A chef Leila Kuczynski, do restaurante Arábia, em São Paulo, mostra como transformar uma batata e uma cebola no melhor acompanhamento que você já comeu! Esta batata à moda libanesa é um must para quem sabe apreciar o luxo da simplicidade.","image":"1142391600000-Batata-a-moda-libanesa","imageFormat":"jpg","imageRatio":0.665644171779141,"imageLocation":"cdn","imageFolder":"receita"}],"isFavorite":false}