{"id":305646,"title":"Batata rosti ","description":"E se a gente preparasse uma clássica batata rosti em versão tamanho família? E se a gente recheasse com queijo meia-cura? Pronto: a ideia toma forma aqui!","imageUrl":"https://cdn.panelinha.com.br/receita/1448589600000-Batata-rosti-para-a-familia.jpg","slug":"Batata-rosti-para-a-familia","content":{"light":false,"author":"Panelinha","serves":"Até 4 porções","keyword":"batata","hasVideo":false,"prepareTime":"Pá-Pum","recipeSteps":[{"body":"<ol>\n<li>Lave, descasque e passe as batatas na parte grossa do ralador.&nbsp;</li>\n<li>Sobre uma tigela, abra um pano de prato limpo e coloque as batatas raladas no centro. Una as pontas do pano, formando uma trouxinha, tor&ccedil;a e esprema bem para extrair toda a &aacute;gua das batatas - isso evita que elas grudem na frigideira na hora de fazer a rosti.&nbsp;</li>\n<li>Despreze toda a &aacute;gua. Abra o pano e tempere as batatas com sal e pimenta-do-reino a gosto.&nbsp;</li>\n<li>Leve ao fogo baixo uma frigideira grande com cerca de 30 cm de di&acirc;metro. Quando aquecer, adicione 1 1/2 colher (sopa) de azeite. Gire a frigideira para untar todo o fundo e laterais com o azeite.&nbsp;</li>\n<li>Mantenha a frigideira em fogo baixo e distribua metade das batatas raladas at&eacute; cobrir o fundo da frigideira. Pressione com uma esp&aacute;tula para formar uma camada uniforme.&nbsp;</li>\n<li>Polvilhe a superf&iacute;cie com o queijo ralado - deixe cerca de 2 cm de toda a borda livre para evitar que o recheio vase e a rosti grude nas laterais. Cubra com o restante das batatas raladas e, com a esp&aacute;tula, pressione para nivelar e selar as laterais. Regue a lateral da frigideira com o restante do azeite para garantir que a rosti solte na hora de virar. Deixe cozinhar em fogo baixo por 12 minutos para dourar a base.&nbsp;</li>\n<li>Para dourar o outro lado: retire a frigideira do fogo e, com a esp&aacute;tula, solte as laterais e o fundo da batata rosti. Deslize toda a rosti sobre um prato grande, cubra com a frigideira e vire de uma s&oacute; vez. Volte a frigideira ao fogo baixo, deixe cozinhar por mais 12 minutos e desligue e fogo.&nbsp;</li>\n<li>Sirva a seguir, diretamente da frigideira. Se preferir, solte as laterais da batata com a esp&aacute;tula e vire sobre um prato para servir.</li>\n</ol>","type":"preparo","title":"","sequence":0,"superTitle":"","ingredients":[{"quantity":"6","sequence":0,"connector":"","measureId":1,"complement":"médias","ingredientId":102},{"quantity":"2/3 de","sequence":1,"connector":"de","measureId":27,"complement":"ralado grosso","ingredientId":1059},{"quantity":"2","sequence":2,"connector":"de","measureId":23,"complement":"","ingredientId":104},{"quantity":"","sequence":3,"connector":"","measureId":1,"complement":"a gosto","ingredientId":73}]},{"type":"produto","title":"Compre o que você precisa","columns":3,"sequence":1,"subtitle":"Loja Panelinha ","isCarousel":false,"productCells":[{"id":371,"tag":"","imageUrl":"https://cdn.panelinha.com.br/produto/1565641301441-51JU9offaRL._SL1000_.jpg","sequence":0,"customTitle":"Jogo com 6 pratos rasos, Noz-moscada","storeUrl":"https://amzn.to/2Us0lz2","image":"1565641301441-51JU9offaRL._SL1000_","imageLocation":"cdn","imageRatio":0.5,"imageFormat":"jpg","imageFolder":"produto"},{"id":301,"tag":"","imageUrl":"https://cdn.panelinha.com.br/produto/1564000208005-tigelavidro.jpg","sequence":1,"customTitle":"Tigela de vidro, Etna"},{"id":50,"tag":"","imageUrl":"https://cdn.panelinha.com.br/produto/1562868472409-raladorquatrofaces.jpg","sequence":2,"customTitle":"Ralador de 4 faces, Cuisipro ","storeUrl":"https://amzn.to/2JpHzC3","image":"1562868472409-raladorquatrofaces","imageLocation":"cdn","imageRatio":1.55696202531646,"imageFormat":"jpg","imageFolder":"produto"},{"id":234,"tag":"","imageUrl":"https://cdn.panelinha.com.br/produto/1563467327005-715OOsS4BQL._SL1500_.jpg","sequence":3,"customTitle":"Frigideira sem revestimento, Zwilling J.A. Henckels","storeUrl":"https://amzn.to/2Jnkik8","image":"1563467327005-715OOsS4BQL._SL1500_","imageLocation":"cdn","imageRatio":0.6,"imageFormat":"jpg","imageFolder":"produto"},{"id":66,"tag":"","imageUrl":"https://cdn.panelinha.com.br/produto/1562871030981-espatula.jpg","sequence":4,"customTitle":"Espátula de inox","storeUrl":"https://amzn.to/3dGmVeQ","image":"1562871030981-espatula","imageLocation":"cdn","imageRatio":1,"imageFormat":"jpg","imageFolder":"produto"},{"id":42,"tag":"","imageUrl":"https://cdn.panelinha.com.br/produto/1562865426656-espatulastaub.jpg","sequence":5,"customTitle":"Espátula de silicone, Staub","storeUrl":"https://amzn.to/2UM09cN","image":"1562865426656-espatulastaub","imageLocation":"cdn","imageRatio":2.44698205546493,"imageFormat":"jpg","imageFolder":"produto"}]}]},"pageType":"receita","categories":[{"id":2,"title":"Acompanhamentos","page_id":305646},{"id":15,"title":"Pratos principais","page_id":305646},{"id":349,"title":"Uma panela só","page_id":305646}],"cuisines":[{"id":16,"title":"vegetariana","page_id":305646},{"id":21,"title":"fusion","page_id":305646},{"id":23,"title":"suiça","page_id":305646},{"id":28,"title":"alemã","page_id":305646},{"id":37,"title":"mediterrânea","page_id":305646},{"id":40,"title":"sem glúten","page_id":305646}],"measures":[{"id":1,"title":null,"page_id":305646},{"id":23,"title":"colheres (sopa)","page_id":305646},{"id":27,"title":"xícara (chá)","page_id":305646}],"ingredients":[{"id":73,"title":"sal e pimenta-do-reino moída na hora","page_id":305646,"links":[]},{"id":102,"title":"batatas","page_id":305646,"links":[]},{"id":104,"title":"azeite","page_id":305646,"links":[]},{"id":1059,"title":"queijo meia-cura","page_id":305646,"links":[]}],"childrenPages":[{"imageurl":"https://cdn.panelinha.com.br/receita/1410490800000-Salada-de-pepino-com-iogurte-e-endro.jpg","slug":"Salada-de-pepino-com-iogurte-e-endro","join_id":305646,"page_id":305394,"customtitle":"Salada de pepino com iogurte e endro","tag":"entrada","sequence":1,"image_url":"https://cdn.panelinha.com.br/receita/1410490800000-Salada-de-pepino-com-iogurte-e-endro.jpg","image":"1410490800000-Salada-de-pepino-com-iogurte-e-endro","image_format":"jpg","image_ratio":0.665644171779141,"image_location":"cdn","image_folder":"receita"},{"imageurl":"https://cdn.panelinha.com.br/receita/1415152800000-Strudel-folhado-de-maca.jpg","slug":"Strudel-folhado-de-maca","join_id":305646,"page_id":305435,"customtitle":"Strudel folhado de maçã","tag":"sobremesa","sequence":4,"image_url":"https://cdn.panelinha.com.br/receita/1415152800000-Strudel-folhado-de-maca.jpg","image":"1415152800000-Strudel-folhado-de-maca","image_format":"jpg","image_ratio":0.665644171779141,"image_location":"cdn","image_folder":"receita"},{"imageurl":"https://cdn.panelinha.com.br/receita/1448589600000-Batata-rosti-para-a-familia.jpg","slug":"Batata-rosti-para-a-familia","join_id":305646,"page_id":305646,"customtitle":"Batata rosti para a família","tag":"acompanhamento","sequence":3,"image_url":"https://cdn.panelinha.com.br/receita/1448589600000-Batata-rosti-para-a-familia.jpg","image":"1448589600000-Batata-rosti-para-a-familia","image_format":"jpg","image_ratio":0.665644171779141,"image_location":"cdn","image_folder":"receita"},{"imageurl":"https://cdn.panelinha.com.br/receita/1448589600000-Espumante-com-sementes-de-roma.jpg","slug":"Espumante-com-sementes-de-roma","join_id":305646,"page_id":305647,"customtitle":"Espumante com sementes de romã","tag":"drinque","sequence":0,"image_url":"https://cdn.panelinha.com.br/receita/1448589600000-Espumante-com-sementes-de-roma.jpg","image":"1448589600000-Espumante-com-sementes-de-roma","image_format":"jpg","image_ratio":0.665644171779141,"image_location":"cdn","image_folder":"receita"},{"imageurl":"https://cdn.panelinha.com.br/receita/1467255600000-Bife-role-recheado-com-ameixa.jpg","slug":"Bife-role-recheado-com-ameixa","join_id":305646,"page_id":305795,"customtitle":"Bife rolê recheado com ameixa","tag":"prato principal","sequence":2,"image_url":"https://cdn.panelinha.com.br/receita/1467255600000-Bife-role-recheado-com-ameixa.jpg","image":"1467255600000-Bife-role-recheado-com-ameixa","image_format":"jpg","image_ratio":0.665644171779141,"image_location":"cdn","image_folder":"receita"}],"image":"1448589600000-Batata-rosti-para-a-familia","imageLocation":"cdn","imageRatio":0.665644171779141,"imageFormat":"jpg","imageFolder":"receita","relatedContent":[{"title":"Batata ao murro de frigideira","imageUrl":"https://cdn.panelinha.com.br/receita/1553283294426-_MGL7532-2.jpg","pageType":"receita","slug":"batatas-murro-frigideira","description":"Com perfume de ervas e limão, as batatas bolinha ficam douradas e crocantes depois de uma passada na frigideira.","image":"1553283294426-_MGL7532-2","imageFormat":"jpg","imageRatio":0.665644171779141,"imageLocation":"cdn","imageFolder":"receita"},{"title":"Batata bolinha assada com alecrim para crianças","imageUrl":"https://cdn.panelinha.com.br/receita/1191812400000-Batata-bolinha-assada-com-alecrim-para-criancas.jpg","pageType":"receita","slug":"Batata-bolinha-assada-com-alecrim-para-criancas","description":"No lugar de batatas fritas, experimente servir para as crianças estas batatas bolinha no copinho. No dia-a-dia, vai bem acompanhando todos os tipos de carne.","image":"1191812400000-Batata-bolinha-assada-com-alecrim-para-criancas","imageFormat":"jpg","imageRatio":0.665644171779141,"imageLocation":"cdn","imageFolder":"receita"},{"title":"Batata bolinha ao murro com sálvia","imageUrl":"https://cdn.panelinha.com.br/receita/1501857395507-batata%20bolinha%20ao%20murro.jpg","pageType":"receita","slug":"Batatas-bolinhas-ao-murro-com-salvia","description":"A receita de batata ao murro é um sucesso do Panelinha. Agora ela ganhou uma versão para dias de festa: com batata bolinha! Uma graça!","image":"1501857395507-batata bolinha ao murro","imageFormat":"jpg","imageRatio":0.665644171779141,"imageLocation":"cdn","imageFolder":"receita"},{"title":"Batata ao curry","imageUrl":"https://cdn.panelinha.com.br/receita/953607600000-Batatas-ao-curry.jpg","pageType":"receita","slug":"Batatas-ao-curry","description":"Saia do lugar-comum e impressione os seus convidados com o sabor desta batata ao curry.","image":"953607600000-Batatas-ao-curry","imageFormat":"jpg","imageRatio":0.665644171779141,"imageLocation":"cdn","imageFolder":"receita"},{"title":"Purê de batata com ervas ","imageUrl":"https://cdn.panelinha.com.br/receita/1584735457754-pur%C3%AA%20com%20ervas.jpg","pageType":"receita","slug":"pure-de-batata-com-ervas","description":"Não vai leite nem manteiga: o azeite é perfumado com alho e ervas. \"Mas e o ponto?!\". Vem com a água do cozimento. Diferente e prático. \n","image":"1584735457754-purê com ervas","imageFormat":"jpg","imageRatio":0.665644171779141,"imageLocation":"cdn","imageFolder":"receita"},{"title":"Batata frita tradicional","imageUrl":"https://cdn.panelinha.com.br/receita/953607600000-Batata-frita-tradicional.jpg","pageType":"receita","slug":"Batata-frita-tradicional","description":"A batata frita é uma delícia, mas tem de ser bem feita! Com as nossas dicas, você terá batatas sequinhas e crocantes.","image":"953607600000-Batata-frita-tradicional","imageFormat":"jpg","imageRatio":0.665644171779141,"imageLocation":"cdn","imageFolder":"receita"}],"isFavorite":false}