{"id":308079,"title":"Cuscuz de brócolis","description":"Passado no processador o brócolis fica com textura de cuscuz marroquino e vira acompanhamento leve e todo cheio de charme para servir com preparos com molho. Ideia boa para quem adora brócolis e quer variar o jeito de servir. ","imageUrl":"https://cdn.panelinha.com.br/receita/1564176768040-CUSCUZ-BRO%CC%81COLIS.jpg","slug":"cuscuz-de-brocolis","content":{"light":false,"author":"Panelinha","serves":"Até 4 porções","keyword":"cuscuz","hasVideo":false,"prepareTime":"Pá-Pum","recipeSteps":[{"body":"<ol>\n<li>Descasque os dentes de alho. Descarte as folhas e a base grossa do talo do br&oacute;colis. Corte o br&oacute;colis em floretes m&eacute;dios, de cerca de 3 cm &ndash; para ficar mais f&aacute;cil, vire o br&oacute;colis de cabe&ccedil;a para baixo e v&aacute; cortando os floretes pela base. Reserve os talos para outra prepara&ccedil;&atilde;o (voc&ecirc; pode fazer uma sopa).</li>\n<li>Lave os floretes em &aacute;gua corrente e seque bem com um pano de prato. Coloque metade dos floretes no processador, junte um dente de alho e bata at&eacute; ficar com a textura de cuscuz marroquino. Transfira para uma tigela e repita com o restante do br&oacute;colis e alho.</li>\n<li>Leve uma panela m&eacute;dia ao fogo baixo. Quando aquecer, regue com o azeite, coloque o br&oacute;colis processado e tempere com sal. Deixe cozinhar por 10 minutos, mexendo de vez em quando, at&eacute; o cuscuz ficar macio e &uacute;mido. Sirva a seguir.</li>\n</ol>\n<p>&nbsp;</p>\n<h4>Pode congelar</h4>\n<p>J&aacute; processado ou mesmo processado e refogado, em sacos herm&eacute;ticos ou marmitas de alum&iacute;nio. Para descongelar: do congelador vai direto para a panela, em fogo m&eacute;dio. Mexa de vez em quando, at&eacute; aquecer e descongelar.</p>","type":"preparo","title":"","sequence":0,"superTitle":"","ingredients":[{"quantity":"1","sequence":0,"connector":"","complement":"ninja grande","ingredientId":291},{"quantity":"2","sequence":1,"connector":"de","measureId":19,"complement":"","ingredientId":90},{"quantity":"2","sequence":2,"connector":"de","measureId":23,"complement":"","ingredientId":104},{"quantity":"","sequence":3,"connector":"","complement":"a gosto","ingredientId":111}]},{"type":"produto","title":"Compre o que você precisa","columns":3,"sequence":1,"subtitle":"Loja Panelinha ","isCarousel":false,"productCells":[{"id":277,"tag":"","imageUrl":"https://cdn.panelinha.com.br/produto/1563565203606-51W7N-BQeRL._SL1000_.jpg","sequence":0,"customTitle":"Processador de Alimentos Philips Walita Viva Vermelho 2 Velocidades + Pulsar 650W 220 Volts","storeUrl":"https://amzn.to/3avMHR0","image":"1563565203606-51W7N-BQeRL._SL1000_","imageLocation":"cdn","imageRatio":1,"imageFormat":"jpg","imageFolder":"produto"},{"id":61,"tag":"","imageUrl":"https://cdn.panelinha.com.br/produto/1562870467930-tabuatramonta.jpg","sequence":1,"customTitle":"Tábua de madeira, Tramontina ","storeUrl":"https://amzn.to/2xyk6Mg","image":"1562870467930-tabuatramonta","imageLocation":"cdn","imageRatio":1,"imageFormat":"jpg","imageFolder":"produto"},{"id":64,"tag":"","imageUrl":"https://cdn.panelinha.com.br/produto/1562870759084-51muMh67gLL._SL1500_.jpg","sequence":2,"customTitle":"Faca de chefe, Zwilling ","storeUrl":"https://amzn.to/2Us3pLq","image":"1562870759084-51muMh67gLL._SL1500_","imageLocation":"cdn","imageRatio":7.07547169811321,"imageFormat":"jpg","imageFolder":"produto"},{"id":326,"tag":"","imageUrl":"https://cdn.panelinha.com.br/produto/1564155320980-panela20tramonta.jpg","sequence":3,"customTitle":"Panela de inox com fundo triplo, 20 cm, Tramontina ","storeUrl":"https://amzn.to/2JsNLJo","image":"1564155320980-panela20tramonta","imageLocation":"cdn","imageRatio":0.6,"imageFormat":"jpg","imageFolder":"produto"},{"id":42,"tag":"","imageUrl":"https://cdn.panelinha.com.br/produto/1562865426656-espatulastaub.jpg","sequence":4,"customTitle":"Espátula de silicone, Staub","storeUrl":"https://amzn.to/2UM09cN","image":"1562865426656-espatulastaub","imageLocation":"cdn","imageRatio":2.44698205546493,"imageFormat":"jpg","imageFolder":"produto"},{"id":10,"tag":"","imageUrl":"https://cdn.panelinha.com.br/produto/1562856483086-51TRfZAoOoL._SL1000_.jpg","sequence":5,"customTitle":"Tigela média [pimenta-do-reino], Acervo Panelinha","storeUrl":"https://amzn.to/2JtZ6ZC","image":"1562856483086-51TRfZAoOoL._SL1000_","imageLocation":"cdn","imageRatio":1,"imageFormat":"jpg","imageFolder":"produto"}]}],"customServes":""},"pageType":"receita","categories":[{"id":2,"title":"Acompanhamentos","page_id":308079},{"id":179,"title":"Cozinha Prática","page_id":308079}],"cuisines":[{"id":1,"title":"contemporânea","page_id":308079},{"id":16,"title":"vegetariana","page_id":308079},{"id":17,"title":"prática","page_id":308079},{"id":40,"title":"sem glúten","page_id":308079}],"measures":[{"id":19,"title":"dentes","page_id":308079},{"id":23,"title":"colheres (sopa)","page_id":308079}],"ingredients":[{"id":90,"title":"alho","page_id":308079,"links":[]},{"id":104,"title":"azeite","page_id":308079,"links":[]},{"id":111,"title":"sal","page_id":308079,"links":[]},{"id":291,"title":"brócolis","page_id":308079,"links":[]}],"childrenPages":[{"imageurl":"https://cdn.panelinha.com.br/receita/1375758000000-Musse-de-limao-siciliano.jpg","slug":"Musse-de-limao-siciliano","join_id":308079,"page_id":305263,"customtitle":"Musse de limão siciliano","tag":"sobremesa","sequence":3,"image_url":"https://cdn.panelinha.com.br/receita/1375758000000-Musse-de-limao-siciliano.jpg","image":"1375758000000-Musse-de-limao-siciliano","image_format":"jpg","image_ratio":0.665644171779141,"image_location":"cdn","image_folder":"receita"},{"imageurl":"https://cdn.panelinha.com.br/receita/1489518658614-amendoim%20temperado%20cu%CC%81rcuma.jpg","slug":"amendoim-curcuma","join_id":308079,"page_id":306073,"customtitle":"Amendoim temperado com cúrcuma","tag":"Entrada","sequence":0,"image_url":"https://cdn.panelinha.com.br/receita/1489518658614-amendoim%20temperado%20cu%CC%81rcuma.jpg","image":"1489518658614-amendoim temperado cúrcuma","image_format":"jpg","image_ratio":0.665644171779141,"image_location":"cdn","image_folder":"receita"},{"imageurl":"https://cdn.panelinha.com.br/receita/1564176118912-fraldinha-assada-cerveja.jpg","slug":"fraldinha-assada-na-cerveja","join_id":308079,"page_id":308078,"customtitle":"Fraldinha assada na cerveja","tag":"Prato principal","sequence":2,"image_url":"https://cdn.panelinha.com.br/receita/1564176118912-fraldinha-assada-cerveja.jpg","image":"1564176118912-fraldinha-assada-cerveja","image_format":"jpg","image_ratio":0.665644171779141,"image_location":"cdn","image_folder":"receita"},{"imageurl":"https://cdn.panelinha.com.br/receita/1564176768040-CUSCUZ-BRO%CC%81COLIS.jpg","slug":"cuscuz-de-brocolis","join_id":308079,"page_id":308079,"customtitle":"Cuscuz de brócolis","tag":"acompanhamento","sequence":1,"image_url":"https://cdn.panelinha.com.br/receita/1564176768040-CUSCUZ-BRO%CC%81COLIS.jpg","image":"1564176768040-CUSCUZ-BRÓCOLIS","image_format":"jpg","image_ratio":0.665644171779141,"image_location":"cdn","image_folder":"receita"}],"image":"1564176768040-CUSCUZ-BRÓCOLIS","imageLocation":"cdn","imageRatio":0.665644171779141,"imageFormat":"jpg","imageFolder":"receita","relatedContent":[{"title":"Cuscuz de milho com ovo pochê","imageUrl":"https://cdn.panelinha.com.br/receita/1575554340132-1544463480412-cuscuz-ovovale.jpg","pageType":"receita","slug":"Cuscuz-nordestino-com-ovo-poche","description":"Conhece a expressão “café da manhã dos campeões”? É este aqui. Serve também para um brunch com ares regionais e até para um jantar leve. ","image":"1575554340132-1544463480412-cuscuz-ovovale","imageFormat":"jpg","imageRatio":0.665644171779141,"imageLocation":"cdn","imageFolder":"receita"},{"title":"Cuscuz de milho com castanha-de-caju","imageUrl":"https://cdn.panelinha.com.br/receita/1586460758991-cuscuz%20de%20milho.jpg","pageType":"receita","slug":"cuscuz-de-milho-com-castanha-de-caju","description":"Cuscuz de milho não é só café da manhã. É um ótimo acompanhamento para variar as refeições. Nesta receita, depois de cozido ele é passado na frigideira com manteiga e castanha para ganhar mais uma camada de sabor e de textura. Ótimo para servir com receitas ensopadas ou com molho.\n","image":"1586460758991-cuscuz de milho","imageFormat":"jpg","imageRatio":0.665644171779141,"imageLocation":"cdn","imageFolder":"receita"},{"title":"Cuscuz marroquino com castanha-de-caju","imageUrl":"https://cdn.panelinha.com.br/receita/1556895983882-CP-2019-19-02_9855.jpg","pageType":"receita","slug":"Cuscuz-marroquino-castanha-de-caju","description":"Um punhado de castanha picada transforma o cuscuz do dia a dia em um acompanhamento mais crocante, mais charmoso, quase festivo. ","image":"1556895983882-CP-2019-19-02_9855","imageFormat":"jpg","imageRatio":0.665644171779141,"imageLocation":"cdn","imageFolder":"receita"},{"title":"Cuscuz paulista de legumes","imageUrl":"https://cdn.panelinha.com.br/receita/1447725600000-Cuscuz-paulista-de-legumes.jpg","pageType":"receita","slug":"Cuscuz-paulista-de-legumes","description":"O primeiro segredo deste cuscuz é o caldo, bem saboroso! O segundo segredo é a decoração, que deixa o prato festivo. Nem precisa ser vegetariano para virar fã.","image":"1447725600000-Cuscuz-paulista-de-legumes","imageFormat":"jpg","imageRatio":0.665644171779141,"imageLocation":"cdn","imageFolder":"receita"},{"title":"Cuscuz paulista de legumes com saladinha de repolho","imageUrl":"https://cdn.panelinha.com.br/receita/1571839162559-cuscuznatal.jpg","pageType":"receita","slug":"Cuscuz-de-legumes-com-saladinha-de-repolho","description":"Clássico em versão de gala, esse cuscuz deve seu sabor a uma combinação incrível de legumes e especiarias. Para ficar com ares de festa, repolho ralado fininho para decorar. E o pulo do gato: o ovo de codorna cozido vai sobre o repolho, na hora de servir, assim não fica com aquele gosto de geladeira.","image":"1571839162559-cuscuznatal","imageFormat":"jpg","imageRatio":0.665644171779141,"imageLocation":"cdn","imageFolder":"receita"},{"title":"Cuscuz paulista","imageUrl":"https://cdn.panelinha.com.br/receita/953607600000-Cuscuz-paulista.jpg","pageType":"receita","slug":"Cuscuz-paulista","description":"Palmito, camarões, peixe, temperos... Quem resiste ao sabor do tradicional cuscuz paulista?","image":"953607600000-Cuscuz-paulista","imageFormat":"jpg","imageRatio":0.665644171779141,"imageLocation":"cdn","imageFolder":"receita"}],"isFavorite":false}