{"id":305698,"title":"Fritata de batata com aspargos","description":"A versão italiana das espanholas tortillas é a pedida para o brunch de domingo. O toque especial fica por conta do sabor suave e delicado dos aspargos. Um luxo!","imageUrl":"https://cdn.panelinha.com.br/receita/1557245457098-fritata.jpg","slug":"Frittata-de-batata-com-aspargos","content":{"light":false,"author":"Panelinha","serves":"Até 6 porções","keyword":"fritata","hasVideo":false,"prepareTime":"Até 1h","recipeSteps":[{"body":"<p>1. Preaque&ccedil;a o forno a 180 &ordm;C (temperatura m&eacute;dia). <br /><br />2. Comece pelos aspargos: lave, seque, corte e descarte um peda&ccedil;o de cerca de 2 cm da base de cada talo (ela &eacute; muito dura e fibrosa); corte e reserve as pontas; fatie o restante dos talos em rodelas de cerca de 0,5 cm. <br /><br />3. Com uma escovinha para legumes, lave bem a casca das batatas sob &aacute;gua corrente. Com um mandolin (fatiador de legumes), corte cada uma em rodelas finas (se preferir, use uma faca). <br /><br />4. Leve ao fogo m&eacute;dio uma frigideira que possa ir ao forno (caso n&atilde;o tenha, comece o preparo na frigideira e, na hora de acrescentar os ovos, transfira tudo para um refrat&aacute;rio). Quando aquecer, regue com 1 colher (sopa) de azeite e acrescente as pontas e fatias de aspargos. Tempere com sal e deixe dourar por cerca de 2 minutos, mexendo de vez em quando com uma esp&aacute;tula.&nbsp;<br /><br />5. Transfira os aspargos para uma tigela e mantenha a frigideira em fogo m&eacute;dio. Regue com mais &frac14; de x&iacute;cara (ch&aacute;) de azeite e adicione as batatas. Tempere com sal e deixe cozinhar por cerca de 7 minutos, virando de vez em quando, at&eacute; as fatias come&ccedil;arem a ficar transparentes. <br /><br />6. Enquanto as batatas cozinham no azeite quebre um ovo de cada vez numa tigela pequena e transfira para outra maior - se um estiver estragado, voc&ecirc; n&atilde;o perde a receita. Tempere com sal e pimenta a gosto e bata bem com um garfo para misturar. <br /><br />7. Assim que as batatas estiverem cozidas, misture as rodelas de aspargos - reserve as pontas para servir - e nivele as batatas com a esp&aacute;tula. Caso sua frigideira n&atilde;o possa ir ao forno, esse &eacute; o momento de transferir os legumes para um refrat&aacute;rio. <br /><br />8. Acrescente os ovos batidos e passe a esp&aacute;tula delicadamente pela borda da frigideira (ou do refrat&aacute;rio) para modelar a fritata. <br /><br />9. Leve a frigideira ao forno e deixe assar por cerca de 25 minutos, at&eacute; a fritata inflar e dourar. Retire do forno e sirva a seguir com as pontas dos aspargos douradas (se preferir, sirva a fritata em temperatura ambiente).</p>\n<h4>N&Atilde;O TEM UMA FRIGIDEIRA T&Atilde;O GRANDE?</h4>\n<p>Voc&ecirc; pode dourar os aspargos e cozinhar as batatas numa panela. Unte um refrat&aacute;rio grande com azeite, disponha as fatias de batatas e aspargos, junte os ovos batidos e leve ao forno para assar.</p>","type":"preparo","title":"","sequence":0,"superTitle":"","ingredients":[{"quantity":"12","sequence":0,"connector":"","measureId":1,"complement":"","ingredientId":44},{"quantity":"4","sequence":1,"connector":"","measureId":1,"complement":"","ingredientId":102},{"quantity":"1","sequence":2,"connector":"de","measureId":123,"complement":"verdes frescos","ingredientId":237},{"quantity":"¼ de","sequence":3,"connector":"de","measureId":27,"complement":"","ingredientId":104},{"quantity":"","sequence":4,"connector":"","measureId":1,"complement":"a gosto","ingredientId":73}]}]},"pageType":"receita","categories":[{"id":2,"title":"Acompanhamentos","page_id":305698},{"id":9,"title":"Café da manhã","page_id":305698},{"id":11,"title":"Entradas","page_id":305698},{"id":15,"title":"Pratos principais","page_id":305698},{"id":328,"title":"Livro O Que Tem na Geladeira? ","page_id":305698},{"id":333,"title":"Ovo","page_id":305698},{"id":336,"title":"Páscoa","page_id":305698},{"id":349,"title":"Uma panela só","page_id":305698}],"cuisines":[{"id":2,"title":"da vovó","page_id":305698},{"id":12,"title":"italiana","page_id":305698},{"id":16,"title":"vegetariana","page_id":305698},{"id":19,"title":"clássica","page_id":305698},{"id":39,"title":"páscoa","page_id":305698},{"id":40,"title":"sem glúten","page_id":305698}],"measures":[{"id":1,"title":null,"page_id":305698},{"id":27,"title":"xícara (chá)","page_id":305698},{"id":123,"title":"maço ","page_id":305698}],"ingredients":[{"id":44,"title":"ovos","page_id":305698,"links":[]},{"id":73,"title":"sal e pimenta-do-reino moída na hora","page_id":305698,"links":[]},{"id":102,"title":"batatas","page_id":305698,"links":[]},{"id":104,"title":"azeite","page_id":305698,"links":[]},{"id":237,"title":"aspargos","page_id":305698,"links":[]}],"childrenPages":[{"imageurl":"https://cdn.panelinha.com.br/receita/1456369200000-Rosca-doce-de-cenoura-com-ameixa.jpg","slug":"Rosca-doce-de-cenoura-com-ameixa","join_id":305698,"page_id":305699,"customtitle":"Rosca doce de cenoura com ameixa","tag":"Sobremesa","sequence":2,"image_url":"https://cdn.panelinha.com.br/receita/1456369200000-Rosca-doce-de-cenoura-com-ameixa.jpg","image":"1456369200000-Rosca-doce-de-cenoura-com-ameixa","image_format":"jpg","image_ratio":0.665644171779141,"image_location":"cdn","image_folder":"receita"},{"imageurl":"https://cdn.panelinha.com.br/receita/1457060400000-Pink-lemonade.jpg","slug":"Pink-lemonade","join_id":305698,"page_id":305717,"customtitle":"Pink lemonade","tag":"Bebida","sequence":0,"image_url":"https://cdn.panelinha.com.br/receita/1457060400000-Pink-lemonade.jpg","image":"1457060400000-Pink-lemonade","image_format":"jpg","image_ratio":0.665644171779141,"image_location":"cdn","image_folder":"receita"},{"imageurl":"https://cdn.panelinha.com.br/receita/1557245457098-fritata.jpg","slug":"Frittata-de-batata-com-aspargos","join_id":305698,"page_id":305698,"customtitle":"Fritata de batata com aspargos","tag":"Prato principal","sequence":1,"image_url":"https://cdn.panelinha.com.br/receita/1557245457098-fritata.jpg","image":"1557245457098-fritata","image_format":"jpg","image_ratio":0.665644171779141,"image_location":"cdn","image_folder":"receita"}],"image":"1557245457098-fritata","imageLocation":"cdn","imageRatio":0.665644171779141,"imageFormat":"jpg","imageFolder":"receita","relatedContent":[{"title":"Fritata de espaguete","imageUrl":"https://cdn.panelinha.com.br/receita/1592932816333-_fritata%20de%20espaguete.jpg","pageType":"receita","slug":"fritata-de-espaguete","description":"Nunca mais você vai comer macarrão esquentado no micro-ondas quando sobrar massa cozida. E de repente pode até perceber que está cozinhando a mais só para sobrar espaguete e garantir uma fritata no dia seguinte... É receita de reaproveitamento que tem tudo para virar favorita.\n","image":"1592932816333-_fritata de espaguete","imageFormat":"jpg","imageRatio":0.665644171779141,"imageLocation":"cdn","imageFolder":"receita"},{"title":"Fritata de mandioquinha com cebola","imageUrl":"https://cdn.panelinha.com.br/receita/1475809200000-Frittata-de-mandioquinha-com-cebola.jpg","pageType":"receita","slug":"Frittata-de-mandioquinha-com-cebola","description":"Fritata é uma prima italiana da omelete, geralmente feita com batata e qualquer outro ingrediente que esteja dando sopa na geladeira. Com mandioquinha fica um arraso. Opção acertadíssima para quando você estiver sozinho.","image":"1475809200000-Frittata-de-mandioquinha-com-cebola","imageFormat":"jpg","imageRatio":0.665644171779141,"imageLocation":"cdn","imageFolder":"receita"},{"title":"Fritata de batata com cebola","imageUrl":"https://cdn.panelinha.com.br/receita/1462244400000-Frittata-de-batata-com-cebola.jpg","pageType":"receita","slug":"Frittata-de-batata-com-cebola","description":"Fritata é a versão italiana da omelete. Essa, com recheio de batata e cebola é finalizada no forno: nem precisa saber virar a omelete na frigideira!","image":"1462244400000-Frittata-de-batata-com-cebola","imageFormat":"jpg","imageRatio":0.665644171779141,"imageLocation":"cdn","imageFolder":"receita"},{"title":"Fritata de batata","imageUrl":"https://cdn.panelinha.com.br/receita/1553891945516-fritata.jpg","pageType":"receita","slug":"Frittata-de-batata","description":"A fritata, uma espécie de prima mais generosa da omelete, pode ser preparada com legumes, queijos, carnes ou que mais a sua imaginação, ou estômago, mandar. E o melhor é que como a receita é para um, você não vai precisar dividir com ninguém!","image":"1553891945516-fritata","imageFormat":"jpg","imageRatio":0.665644171779141,"imageLocation":"cdn","imageFolder":"receita"},{"title":"Fritata de espaguete à carbonara","imageUrl":"https://cdn.panelinha.com.br/receita/1598641891545-fritata-op.jpg","pageType":"receita","slug":"fritata-de-espaguete-carbonara","description":"A sobra de espaguete cozido se transforma em um jantar especial. Com ovos, bacon e parmesão, vira uma versão fritata do clássico carbonara! Pode até acontecer de você começar a cozinhar a mais para sobrar espaguete e garantir a fritata no dia seguinte.\n","image":"1598641891545-fritata-op","imageFormat":"jpg","imageRatio":0.665644171779141,"imageLocation":"cdn","imageFolder":"receita"}],"isFavorite":false}