{"id":308591,"title":"Repolho macerado com cominho e mostarda","description":"O repolho ganha uma massagem perfumada e você ganha um acompanhamento delicioso em coisa de 15 minutos.  Os segredos são a técnica de macerar e a mistura de especiarias quentes batidas no pilão e misturadas ao azeite e vinagre.\n","imageUrl":"https://cdn.panelinha.com.br/receita/1585589643165-repolho%20macerado.jpg","slug":"repolho-macerado-com-cominho-e-mostarda","content":{"light":false,"author":"Panelinha","serves":"Até 2 porções","keyword":"repolho","hasVideo":false,"prepareTime":"Pá-Pum","recipeSteps":[{"body":"<ol>\n<li>Com um fatiador de legumes (ou mandolim) corte o repolho em fatias finas &ndash; v&aacute; passando o repolho pelo mandolim, com cuidado para n&atilde;o fatiar o miolo central que &eacute; muito firme. Se preferir, descarte o miolo e fatie o repolho fino com uma faca &ndash; no total voc&ecirc; precisa de cerca de 4 x&iacute;caras (ch&aacute;) dele fatiado.&nbsp;</li>\n<li>Transfira o repolho para um escorredor e lave bem sob &aacute;gua corrente. Encaixe o escorredor sobre uma tigela, tempere com o sal e misture com as m&atilde;os, massageando o repolho &ndash; o sal drena o excesso de &aacute;gua das folhas, deixando o repolho macio e com o sabor mais suave. Aperte bem para tirar o excesso de &aacute;gua e transfira para uma tigela.</li>\n<li>Numa frigideira pequena, coloque a mostarda, o cominho e leve ao fogo m&eacute;dio para aquecer por 1 minuto e liberar os aromas. Transfira para o pil&atilde;o e quebre as sementes. Misture o vinagre e o azeite nas especiarias ainda quentes e regue sobre o repolho macerado. Misture bem e sirva seguir.</li>\n</ol>\n<p>&nbsp;</p>\n<p>OBS: se preferir, mantenha o repolho macerado na geladeira at&eacute; a hora de servir, ele fica ainda mais gostoso gelado.</p>","type":"preparo","title":"","sequence":0,"superTitle":"","ingredients":[{"quantity":"1/2","sequence":0,"connector":"","complement":"roxo pequeno (cerca de 400 g)","ingredientId":128},{"quantity":"1/2","sequence":1,"connector":"de","measureId":25,"complement":"","ingredientId":276},{"quantity":"1/2","sequence":2,"connector":"de","measureId":25,"complement":"","ingredientId":836},{"quantity":"2","sequence":3,"connector":"de","measureId":23,"complement":"","ingredientId":52},{"quantity":"2","sequence":4,"connector":"de","measureId":23,"complement":"","ingredientId":104},{"quantity":"1","sequence":5,"connector":"de ","measureId":25,"complement":"","ingredientId":111}]},{"type":"produto","title":"Compre o que você precisa","columns":3,"sequence":1,"subtitle":"Loja Panelinha ","isCarousel":false,"productCells":[{"id":348,"tag":"","imageUrl":"https://cdn.panelinha.com.br/produto/1565099987749-mando_amazon.jpg","sequence":0,"customTitle":"Fatiador de cerâmica, Kyocera","storeUrl":"https://amzn.to/2QZ0nMB","image":"1565099987749-mando_amazon","imageLocation":"cdn","imageRatio":1,"imageFormat":"jpg","imageFolder":"produto"},{"id":10,"tag":"","imageUrl":"https://cdn.panelinha.com.br/produto/1562856483086-51TRfZAoOoL._SL1000_.jpg","sequence":1,"customTitle":"Tigela média [pimenta-do-reino], Acervo Panelinha","storeUrl":"https://amzn.to/2JtZ6ZC","image":"1562856483086-51TRfZAoOoL._SL1000_","imageLocation":"cdn","imageRatio":1,"imageFormat":"jpg","imageFolder":"produto"},{"id":203,"tag":"","imageUrl":"https://cdn.panelinha.com.br/produto/1563391965762-A1KB95xo7eL._SL1500_.jpg","sequence":2,"customTitle":"Pilão e mortar de pedra, BSF ","storeUrl":"https://amzn.to/2QWbB4w","image":"1563391965762-A1KB95xo7eL._SL1500_","imageLocation":"cdn","imageRatio":1.0351966873706,"imageFormat":"jpg","imageFolder":"produto"}]}],"customServes":""},"pageType":"receita","categories":[{"id":2,"title":"Acompanhamentos","page_id":308591},{"id":20,"title":"Saladas","page_id":308591},{"id":179,"title":"Cozinha Prática","page_id":308591},{"id":334,"title":"Para dois","page_id":308591}],"cuisines":[{"id":1,"title":"contemporânea","page_id":308591},{"id":16,"title":"vegetariana","page_id":308591},{"id":17,"title":"prática","page_id":308591},{"id":28,"title":"alemã","page_id":308591},{"id":40,"title":"sem glúten","page_id":308591}],"measures":[{"id":23,"title":"colheres (sopa)","page_id":308591},{"id":25,"title":"colher (chá)","page_id":308591}],"ingredients":[{"id":52,"title":"vinagre de vinho branco","page_id":308591,"links":[]},{"id":104,"title":"azeite","page_id":308591,"links":[]},{"id":111,"title":"sal","page_id":308591,"links":[]},{"id":128,"title":"repolho","page_id":308591,"links":[]},{"id":276,"title":"semente de cominho","page_id":308591,"links":[]},{"id":836,"title":"sementes de mostarda","page_id":308591,"links":[]}],"childrenPages":[{"imageurl":"https://cdn.panelinha.com.br/receita/1445306400000-Pudim-rapido-de-tapioca.jpg","slug":"Pudim-rapido-de-tapioca","join_id":308591,"page_id":305606,"customtitle":"Pudim rápido de tapioca","tag":"sobremesa","sequence":3,"image_url":"https://cdn.panelinha.com.br/receita/1445306400000-Pudim-rapido-de-tapioca.jpg","image":"1445306400000-Pudim-rapido-de-tapioca","image_format":"jpg","image_ratio":0.665644171779141,"image_location":"cdn","image_folder":"receita"},{"imageurl":"https://cdn.panelinha.com.br/receita/1468292400000-Lombo-de-porco.jpg","slug":"Lombo-de-porco","join_id":308591,"page_id":305831,"customtitle":"Lombo de porco","tag":"prato principal","sequence":2,"image_url":"https://cdn.panelinha.com.br/receita/1468292400000-Lombo-de-porco.jpg","image":"1468292400000-Lombo-de-porco","image_format":"jpg","image_ratio":0.665644171779141,"image_location":"cdn","image_folder":"receita"},{"imageurl":"https://cdn.panelinha.com.br/receita/1493746381417-_AY_9530.jpg","slug":"feijao-branco-alecrim","join_id":308591,"page_id":306235,"customtitle":"Feijão-branco com alecrim","tag":"acompanhamento","sequence":1,"image_url":"https://cdn.panelinha.com.br/receita/1493746381417-_AY_9530.jpg","image":"1493746381417-_AY_9530","image_format":"jpg","image_ratio":0.667177914110429,"image_location":"cdn","image_folder":"receita"},{"imageurl":"https://cdn.panelinha.com.br/receita/1585589643165-repolho%20macerado.jpg","slug":"repolho-macerado-com-cominho-e-mostarda","join_id":308591,"page_id":308591,"customtitle":"Repolho macerado com cominho e mostarda","tag":"acompanhamento","sequence":0,"image_url":"https://cdn.panelinha.com.br/receita/1585589643165-repolho%20macerado.jpg","image":"1585589643165-repolho macerado","image_format":"jpg","image_ratio":0.665644171779141,"image_location":"cdn","image_folder":"receita"}],"image":"1585589643165-repolho macerado","imageLocation":"cdn","imageRatio":0.665644171779141,"imageFormat":"jpg","imageFolder":"receita","relatedContent":[{"title":"Repolho grelhado","imageUrl":"https://cdn.panelinha.com.br/receita/1338865200000-Repolho-grelhado.jpg","pageType":"receita","slug":"Repolho-grelhado","description":"Quem torce o nariz para o repolho desta vez vai mudar de ideia. Grelhado, ele fica mais atraente e com um sabor suave, ideal para acompanhar carnes vermelhas. Capriche na apresentação e conquiste o paladar de todos na mesa!","image":"1338865200000-Repolho-grelhado","imageFormat":"jpg","imageRatio":0.665644171779141,"imageLocation":"cdn","imageFolder":"receita"},{"title":"Repolho grelhado com bacon para um","imageUrl":"https://cdn.panelinha.com.br/receita/1579787117615-repolho-grelhado.jpg","pageType":"receita","slug":"repolho-bacon-para-um","description":"Tem legume que facilita a vida de quem mora sozinho. Repolho é assim: dura bastante e se transforma em acompanhamentos bem diferentes, para não bater aquela canseira de comer sempre a mesma coisa. Grelhado com bacon, emplaca até como estrela de um pê-efe. ","image":"1579787117615-repolho-grelhado","imageFormat":"jpg","imageRatio":0.665644171779141,"imageLocation":"cdn","imageFolder":"receita"},{"title":"Repolho roxo com maçã","imageUrl":"https://cdn.panelinha.com.br/receita/955681200000-Repolho-roxo-com-maca.jpg","pageType":"receita","slug":"Repolho-roxo-com-maca","description":"O repolho roxo entra em campo para dar um show de bola. Os companheiros de time são maçã e vinagre de vinho branco, que deixam a preparação com sotaque alemão. Espetacular para servir com carne de porco.","image":"955681200000-Repolho-roxo-com-maca","imageFormat":"jpg","imageRatio":0.665644171779141,"imageLocation":"cdn","imageFolder":"receita"},{"title":"Repolho assado com parmesão","imageUrl":"https://cdn.panelinha.com.br/receita/1334199600000-Repolho-assado.jpg","pageType":"receita","slug":"Repolho-assado","description":"Aqui no Panelinha, a gente ama assar legume. Este repolho assado com um pouquinho que queijo parmesão é ideal para acompanhar todos os tipos de carnes, aves e peixes.","image":"1334199600000-Repolho-assado","imageFormat":"jpg","imageRatio":0.665644171779141,"imageLocation":"cdn","imageFolder":"receita"},{"title":"Repolho assado com bacon","imageUrl":"https://cdn.panelinha.com.br/receita/1468292400000-Repolho-assado-com-bacon.jpg","pageType":"receita","slug":"Repolho-assado-com-bacon","description":"Repolho assado é surpreendente. Só com azeite já fica uma maravilha, mas se você quiser dar aquela caprichada: bacon nele! É drible certeiro para escapar da monotonia.","image":"1468292400000-Repolho-assado-com-bacon","imageFormat":"jpg","imageRatio":0.665644171779141,"imageLocation":"cdn","imageFolder":"receita"},{"title":"Salada oriental de repolho","imageUrl":"https://cdn.panelinha.com.br/receita/1468292400000-Salada-de-repolho-oriental.jpg","pageType":"receita","slug":"Salada-de-repolho-oriental","description":"No churrasco do fim de semana, esta salada não pode faltar. A jogada de mestre é o tempero oriental, feito com shoyu, óleo de milho e vinagre de arroz, e a finalização com gergelim preto.","image":"1468292400000-Salada-de-repolho-oriental","imageFormat":"jpg","imageRatio":0.665644171779141,"imageLocation":"cdn","imageFolder":"receita"}],"isFavorite":false}